smo/__init__.py
smo/api.py
smo/background.py
smo/smo.py
smo/examples/usage.ipynb
smo/plugins/napari.py
smo/plugins/cellprofiler/smo.py
smo/plugins/imagej/smo.py
smo/tests/test_smo.py
smo-2.0.2.dist-info/LICENSE.txt
smo-2.0.2.dist-info/METADATA
smo-2.0.2.dist-info/WHEEL
smo-2.0.2.dist-info/entry_points.txt
smo-2.0.2.dist-info/top_level.txt
smo-2.0.2.dist-info/RECORD
