Metadata-Version: 2.1
Name: smo
Version: 2.0.2
Summary: Implementation of the Silver Mountain Operator (SMO) for the estimation of background distributions.
Home-page: https://github.com/maurosilber/smo
Author: Mauro Silberberg
Author-email: maurosilber@gmail.com
License: MIT
Keywords: background,fluorescence,microscopy,imaging
Classifier: Intended Audience :: Science/Research
Classifier: License :: OSI Approved :: MIT License
Classifier: Operating System :: MacOS :: MacOS X
Classifier: Operating System :: Microsoft :: Windows
Classifier: Operating System :: POSIX
Classifier: Programming Language :: Python
Classifier: Programming Language :: Python :: 3.7
Classifier: Programming Language :: Python :: 3.8
Classifier: Programming Language :: Python :: 3.9
Classifier: Programming Language :: Python :: 3.10
Classifier: Programming Language :: Python :: 3.11
Classifier: Topic :: Scientific/Engineering
Classifier: Framework :: napari
License-File: LICENSE.txt
Requires-Dist: numpy
Requires-Dist: scipy
Requires-Dist: typing-extensions ; python_version < "3.9"
Provides-Extra: dev
Requires-Dist: pre-commit ; extra == 'dev'
Requires-Dist: pytest ; extra == 'dev'
Requires-Dist: tox ; extra == 'dev'
